[
  {
    "x": "2013-01-01T00:00:00.000Z",
    "bev": 657,
    "total": 2933323
  },
  {
    "x": "2013-02-01T00:00:00.000Z",
    "bev": 1314,
    "total": 2932522
  },
  {
    "x": "2013-03-01T00:00:00.000Z",
    "bev": 1971,
    "total": 2931716
  },
  {
    "x": "2013-04-01T00:00:00.000Z",
    "bev": 2628,
    "total": 2930905
  },
  {
    "x": "2013-05-01T00:00:00.000Z",
    "bev": 3284,
    "total": 2930090
  },
  {
    "x": "2013-06-01T00:00:00.000Z",
    "bev": 3941,
    "total": 2929270
  },
  {
    "x": "2013-07-01T00:00:00.000Z",
    "bev": 4597,
    "total": 2928446
  },
  {
    "x": "2013-08-01T00:00:00.000Z",
    "bev": 5254,
    "total": 2927617
  },
  {
    "x": "2013-09-01T00:00:00.000Z",
    "bev": 5910,
    "total": 2926784
  },
  {
    "x": "2013-10-01T00:00:00.000Z",
    "bev": 6566,
    "total": 2925947
  },
  {
    "x": "2013-11-01T00:00:00.000Z",
    "bev": 7222,
    "total": 2925105
  },
  {
    "x": "2013-12-01T00:00:00.000Z",
    "bev": 7878,
    "total": 2924260
  },
  {
    "x": "2014-01-01T00:00:00.000Z",
    "bev": 9385,
    "total": 2923582
  },
  {
    "x": "2014-02-01T00:00:00.000Z",
    "bev": 10892,
    "total": 2922900
  },
  {
    "x": "2014-03-01T00:00:00.000Z",
    "bev": 12398,
    "total": 2922214
  },
  {
    "x": "2014-04-01T00:00:00.000Z",
    "bev": 13905,
    "total": 2921524
  },
  {
    "x": "2014-05-01T00:00:00.000Z",
    "bev": 15411,
    "total": 2920831
  },
  {
    "x": "2014-06-01T00:00:00.000Z",
    "bev": 16917,
    "total": 2920135
  },
  {
    "x": "2014-07-01T00:00:00.000Z",
    "bev": 18422,
    "total": 2919434
  },
  {
    "x": "2014-08-01T00:00:00.000Z",
    "bev": 19928,
    "total": 2918731
  },
  {
    "x": "2014-09-01T00:00:00.000Z",
    "bev": 21433,
    "total": 2918024
  },
  {
    "x": "2014-10-01T00:00:00.000Z",
    "bev": 22938,
    "total": 2917314
  },
  {
    "x": "2014-11-01T00:00:00.000Z",
    "bev": 24442,
    "total": 2916600
  },
  {
    "x": "2014-12-01T00:00:00.000Z",
    "bev": 25947,
    "total": 2915884
  },
  {
    "x": "2015-01-01T00:00:00.000Z",
    "bev": 28092,
    "total": 2915705
  },
  {
    "x": "2015-02-01T00:00:00.000Z",
    "bev": 30237,
    "total": 2915522
  },
  {
    "x": "2015-03-01T00:00:00.000Z",
    "bev": 32381,
    "total": 2915337
  },
  {
    "x": "2015-04-01T00:00:00.000Z",
    "bev": 34525,
    "total": 2915148
  },
  {
    "x": "2015-05-01T00:00:00.000Z",
    "bev": 36669,
    "total": 2914957
  },
  {
    "x": "2015-06-01T00:00:00.000Z",
    "bev": 38813,
    "total": 2914763
  },
  {
    "x": "2015-07-01T00:00:00.000Z",
    "bev": 40956,
    "total": 2914566
  },
  {
    "x": "2015-08-01T00:00:00.000Z",
    "bev": 43098,
    "total": 2914367
  },
  {
    "x": "2015-09-01T00:00:00.000Z",
    "bev": 45241,
    "total": 2914165
  },
  {
    "x": "2015-10-01T00:00:00.000Z",
    "bev": 47382,
    "total": 2913961
  },
  {
    "x": "2015-11-01T00:00:00.000Z",
    "bev": 49524,
    "total": 2913754
  },
  {
    "x": "2015-12-01T00:00:00.000Z",
    "bev": 51665,
    "total": 2913544
  },
  {
    "x": "2016-01-01T00:00:00.000Z",
    "bev": 53562,
    "total": 2911766
  },
  {
    "x": "2016-02-01T00:00:00.000Z",
    "bev": 55481,
    "total": 2911217
  },
  {
    "x": "2016-03-01T00:00:00.000Z",
    "bev": 58068,
    "total": 2912319
  },
  {
    "x": "2016-04-01T00:00:00.000Z",
    "bev": 60052,
    "total": 2913659
  },
  {
    "x": "2016-05-01T00:00:00.000Z",
    "bev": 61465,
    "total": 2913746
  },
  {
    "x": "2016-06-01T00:00:00.000Z",
    "bev": 63360,
    "total": 2914646
  },
  {
    "x": "2016-07-01T00:00:00.000Z",
    "bev": 64452,
    "total": 2912904
  },
  {
    "x": "2016-08-01T00:00:00.000Z",
    "bev": 66455,
    "total": 2913352
  },
  {
    "x": "2016-09-01T00:00:00.000Z",
    "bev": 69072,
    "total": 2914420
  },
  {
    "x": "2016-10-01T00:00:00.000Z",
    "bev": 70921,
    "total": 2913563
  },
  {
    "x": "2016-11-01T00:00:00.000Z",
    "bev": 73475,
    "total": 2913967
  },
  {
    "x": "2016-12-01T00:00:00.000Z",
    "bev": 75780,
    "total": 2914777
  },
  {
    "x": "2017-01-01T00:00:00.000Z",
    "bev": 78115,
    "total": 2915038
  },
  {
    "x": "2017-02-01T00:00:00.000Z",
    "bev": 79996,
    "total": 2914030
  },
  {
    "x": "2017-03-01T00:00:00.000Z",
    "bev": 82917,
    "total": 2914630
  },
  {
    "x": "2017-04-01T00:00:00.000Z",
    "bev": 84648,
    "total": 2913170
  },
  {
    "x": "2017-05-01T00:00:00.000Z",
    "bev": 86843,
    "total": 2914544
  },
  {
    "x": "2017-06-01T00:00:00.000Z",
    "bev": 90830,
    "total": 2915969
  },
  {
    "x": "2017-07-01T00:00:00.000Z",
    "bev": 92655,
    "total": 2914641
  },
  {
    "x": "2017-08-01T00:00:00.000Z",
    "bev": 95511,
    "total": 2915250
  },
  {
    "x": "2017-09-01T00:00:00.000Z",
    "bev": 99417,
    "total": 2915927
  },
  {
    "x": "2017-10-01T00:00:00.000Z",
    "bev": 102124,
    "total": 2915590
  },
  {
    "x": "2017-11-01T00:00:00.000Z",
    "bev": 104899,
    "total": 2916522
  },
  {
    "x": "2017-12-01T00:00:00.000Z",
    "bev": 109385,
    "total": 2919787
  },
  {
    "x": "2018-01-01T00:00:00.000Z",
    "bev": 111491,
    "total": 2917574
  },
  {
    "x": "2018-02-01T00:00:00.000Z",
    "bev": 113668,
    "total": 2914950
  },
  {
    "x": "2018-03-01T00:00:00.000Z",
    "bev": 119010,
    "total": 2917982
  },
  {
    "x": "2018-04-01T00:00:00.000Z",
    "bev": 123525,
    "total": 2920942
  },
  {
    "x": "2018-05-01T00:00:00.000Z",
    "bev": 127438,
    "total": 2923092
  },
  {
    "x": "2018-06-01T00:00:00.000Z",
    "bev": 132457,
    "total": 2928391
  },
  {
    "x": "2018-07-01T00:00:00.000Z",
    "bev": 135530,
    "total": 2926978
  },
  {
    "x": "2018-08-01T00:00:00.000Z",
    "bev": 141057,
    "total": 2931050
  },
  {
    "x": "2018-09-01T00:00:00.000Z",
    "bev": 147088,
    "total": 2930917
  },
  {
    "x": "2018-10-01T00:00:00.000Z",
    "bev": 152652,
    "total": 2931707
  },
  {
    "x": "2018-11-01T00:00:00.000Z",
    "bev": 158815,
    "total": 2933117
  },
  {
    "x": "2018-12-01T00:00:00.000Z",
    "bev": 164498,
    "total": 2933860
  },
  {
    "x": "2019-01-01T00:00:00.000Z",
    "bev": 168658,
    "total": 2931374
  },
  {
    "x": "2019-02-01T00:00:00.000Z",
    "bev": 173704,
    "total": 2930845
  },
  {
    "x": "2019-03-01T00:00:00.000Z",
    "bev": 185030,
    "total": 2937735
  },
  {
    "x": "2019-04-01T00:00:00.000Z",
    "bev": 189987,
    "total": 2937409
  },
  {
    "x": "2019-05-01T00:00:00.000Z",
    "bev": 195235,
    "total": 2939217
  },
  {
    "x": "2019-06-01T00:00:00.000Z",
    "bev": 203186,
    "total": 2943114
  },
  {
    "x": "2019-07-01T00:00:00.000Z",
    "bev": 207147,
    "total": 2941041
  },
  {
    "x": "2019-08-01T00:00:00.000Z",
    "bev": 212462,
    "total": 2941885
  },
  {
    "x": "2019-09-01T00:00:00.000Z",
    "bev": 219078,
    "total": 2941552
  },
  {
    "x": "2019-10-01T00:00:00.000Z",
    "bev": 223378,
    "total": 2940440
  },
  {
    "x": "2019-11-01T00:00:00.000Z",
    "bev": 227463,
    "total": 2938587
  },
  {
    "x": "2019-12-01T00:00:00.000Z",
    "bev": 231109,
    "total": 2937681
  },
  {
    "x": "2020-01-01T00:00:00.000Z",
    "bev": 235551,
    "total": 2935248
  },
  {
    "x": "2020-02-01T00:00:00.000Z",
    "bev": 240842,
    "total": 2933638
  },
  {
    "x": "2020-03-01T00:00:00.000Z",
    "bev": 247948,
    "total": 2933960
  },
  {
    "x": "2020-04-01T00:00:00.000Z",
    "bev": 251681,
    "total": 2929140
  },
  {
    "x": "2020-05-01T00:00:00.000Z",
    "bev": 255174,
    "total": 2925248
  },
  {
    "x": "2020-06-01T00:00:00.000Z",
    "bev": 260364,
    "total": 2924906
  },
  {
    "x": "2020-07-01T00:00:00.000Z",
    "bev": 264805,
    "total": 2923178
  },
  {
    "x": "2020-08-01T00:00:00.000Z",
    "bev": 270560,
    "total": 2922568
  },
  {
    "x": "2020-09-01T00:00:00.000Z",
    "bev": 280366,
    "total": 2926717
  },
  {
    "x": "2020-10-01T00:00:00.000Z",
    "bev": 288536,
    "total": 2928079
  },
  {
    "x": "2020-11-01T00:00:00.000Z",
    "bev": 295905,
    "total": 2928810
  },
  {
    "x": "2020-12-01T00:00:00.000Z",
    "bev": 309918,
    "total": 2937398
  },
  {
    "x": "2021-01-01T00:00:00.000Z",
    "bev": 315787,
    "total": 2935704
  },
  {
    "x": "2021-02-01T00:00:00.000Z",
    "bev": 321192,
    "total": 2934618
  },
  {
    "x": "2021-03-01T00:00:00.000Z",
    "bev": 330299,
    "total": 2938487
  },
  {
    "x": "2021-04-01T00:00:00.000Z",
    "bev": 338115,
    "total": 2940322
  },
  {
    "x": "2021-05-01T00:00:00.000Z",
    "bev": 347159,
    "total": 2943065
  },
  {
    "x": "2021-06-01T00:00:00.000Z",
    "bev": 360733,
    "total": 2952519
  },
  {
    "x": "2021-07-01T00:00:00.000Z",
    "bev": 367568,
    "total": 2951978
  },
  {
    "x": "2021-08-01T00:00:00.000Z",
    "bev": 379766,
    "total": 2955551
  },
  {
    "x": "2021-09-01T00:00:00.000Z",
    "bev": 394031,
    "total": 2960689
  },
  {
    "x": "2021-10-01T00:00:00.000Z",
    "bev": 402387,
    "total": 2959413
  },
  {
    "x": "2021-11-01T00:00:00.000Z",
    "bev": 413978,
    "total": 2961832
  },
  {
    "x": "2021-12-01T00:00:00.000Z",
    "bev": 428026,
    "total": 2969543
  },
  {
    "x": "2022-01-01T00:00:00.000Z",
    "bev": 434568,
    "total": 2964642
  },
  {
    "x": "2022-02-01T00:00:00.000Z",
    "bev": 440607,
    "total": 2959933
  },
  {
    "x": "2022-03-01T00:00:00.000Z",
    "bev": 454466,
    "total": 2963314
  },
  {
    "x": "2022-04-01T00:00:00.000Z",
    "bev": 461539,
    "total": 2960180
  },
  {
    "x": "2022-05-01T00:00:00.000Z",
    "bev": 469852,
    "total": 2958859
  },
  {
    "x": "2022-06-01T00:00:00.000Z",
    "bev": 481432,
    "total": 2960901
  },
  {
    "x": "2022-07-01T00:00:00.000Z",
    "bev": 486415,
    "total": 2955290
  },
  {
    "x": "2022-08-01T00:00:00.000Z",
    "bev": 495519,
    "total": 2954795
  },
  {
    "x": "2022-09-01T00:00:00.000Z",
    "bev": 506755,
    "total": 2956583
  },
  {
    "x": "2022-10-01T00:00:00.000Z",
    "bev": 516329,
    "total": 2956283
  },
  {
    "x": "2022-11-01T00:00:00.000Z",
    "bev": 532088,
    "total": 2962935
  },
  {
    "x": "2022-12-01T00:00:00.000Z",
    "bev": 564641,
    "total": 2989571
  },
  {
    "x": "2023-01-01T00:00:00.000Z",
    "bev": 565712,
    "total": 2978568
  },
  {
    "x": "2023-02-01T00:00:00.000Z",
    "bev": 571725,
    "total": 2973145
  },
  {
    "x": "2023-03-01T00:00:00.000Z",
    "bev": 588363,
    "total": 2979650
  },
  {
    "x": "2023-04-01T00:00:00.000Z",
    "bev": 595655,
    "total": 2975764
  },
  {
    "x": "2023-05-01T00:00:00.000Z",
    "bev": 606243,
    "total": 2976244
  },
  {
    "x": "2023-06-01T00:00:00.000Z",
    "bev": 618855,
    "total": 2978948
  },
  {
    "x": "2023-07-01T00:00:00.000Z",
    "bev": 624809,
    "total": 2973611
  },
  {
    "x": "2023-08-01T00:00:00.000Z",
    "bev": 633861,
    "total": 2971832
  },
  {
    "x": "2023-09-01T00:00:00.000Z",
    "bev": 642658,
    "total": 2969312
  },
  {
    "x": "2023-10-01T00:00:00.000Z",
    "bev": 649966,
    "total": 2965376
  },
  {
    "x": "2023-11-01T00:00:00.000Z",
    "bev": 658194,
    "total": 2962863
  },
  {
    "x": "2023-12-01T00:00:00.000Z",
    "bev": 666933,
    "total": 2962185
  },
  {
    "x": "2024-01-01T00:00:00.000Z",
    "bev": 671426,
    "total": 2954446
  },
  {
    "x": "2024-02-01T00:00:00.000Z",
    "bev": 677240,
    "total": 2948264
  },
  {
    "x": "2024-03-01T00:00:00.000Z",
    "bev": 685714,
    "total": 2945155
  },
  {
    "x": "2024-04-01T00:00:00.000Z",
    "bev": 695526,
    "total": 2943537
  },
  {
    "x": "2024-05-01T00:00:00.000Z",
    "bev": 703173,
    "total": 2940932
  },
  {
    "x": "2024-06-01T00:00:00.000Z",
    "bev": 716926,
    "total": 2945590
  },
  {
    "x": "2024-07-01T00:00:00.000Z",
    "bev": 722601,
    "total": 2939188
  },
  {
    "x": "2024-08-01T00:00:00.000Z",
    "bev": 732817,
    "total": 2937445
  },
  {
    "x": "2024-09-01T00:00:00.000Z",
    "bev": 745042,
    "total": 2937700
  },
  {
    "x": "2024-10-01T00:00:00.000Z",
    "bev": 755627,
    "total": 2936395
  },
  {
    "x": "2024-11-01T00:00:00.000Z",
    "bev": 766283,
    "total": 2935227
  },
  {
    "x": "2024-12-01T00:00:00.000Z",
    "bev": 777660,
    "total": 2936023
  },
  {
    "x": "2025-01-01T00:00:00.000Z",
    "bev": 786316,
    "total": 2932510
  },
  {
    "x": "2025-02-01T00:00:00.000Z",
    "bev": 794488,
    "total": 2928604
  },
  {
    "x": "2025-03-01T00:00:00.000Z",
    "bev": 805368,
    "total": 2929053
  },
  {
    "x": "2025-04-01T00:00:00.000Z",
    "bev": 815991,
    "total": 2927485
  },
  {
    "x": "2025-05-01T00:00:00.000Z",
    "bev": 829048,
    "total": 2928891
  },
  {
    "x": "2025-06-01T00:00:00.000Z",
    "bev": 846512,
    "total": 2934410
  },
  {
    "x": "2025-07-01T00:00:00.000Z",
    "bev": 855459,
    "total": 2931119
  },
  {
    "x": "2025-08-01T00:00:00.000Z",
    "bev": 868590,
    "total": 2932181
  },
  {
    "x": "2025-09-01T00:00:00.000Z",
    "bev": 882314,
    "total": 2933742
  },
  {
    "x": "2025-10-01T00:00:00.000Z",
    "bev": 892797,
    "total": 2932027
  },
  {
    "x": "2025-11-01T00:00:00.000Z",
    "bev": 911847,
    "total": 2939072
  },
  {
    "x": "2025-12-01T00:00:00.000Z",
    "bev": 945807,
    "total": 2961407
  },
  {
    "x": "2026-01-01T00:00:00.000Z",
    "bev": 947492,
    "total": 2950768
  },
  {
    "x": "2026-02-01T00:00:00.000Z",
    "bev": 954213,
    "total": 2945186
  },
  {
    "x": "2026-03-01T00:00:00.000Z",
    "bev": 971204,
    "total": 2950019
  },
  {
    "x": "2026-04-01T00:00:00.000Z",
    "bev": 981730,
    "total": 2948269
  },
  {
    "x": "2026-05-01T00:00:00.000Z",
    "bev": 992626,
    "total": 2948314
  },
  {
    "x": "2026-06-01T00:00:00.000Z",
    "bev": 1003524,
    "total": 2948360
  },
  {
    "x": "2026-07-01T00:00:00.000Z",
    "bev": 1014423,
    "total": 2948406
  },
  {
    "x": "2026-08-01T00:00:00.000Z",
    "bev": 1025322,
    "total": 2948453
  },
  {
    "x": "2026-09-01T00:00:00.000Z",
    "bev": 1036222,
    "total": 2948500
  },
  {
    "x": "2026-10-01T00:00:00.000Z",
    "bev": 1047121,
    "total": 2948547
  },
  {
    "x": "2026-11-01T00:00:00.000Z",
    "bev": 1058018,
    "total": 2948595
  },
  {
    "x": "2026-12-01T00:00:00.000Z",
    "bev": 1068914,
    "total": 2948644
  },
  {
    "x": "2027-01-01T00:00:00.000Z",
    "bev": 1079807,
    "total": 2948693
  },
  {
    "x": "2027-02-01T00:00:00.000Z",
    "bev": 1090698,
    "total": 2948742
  },
  {
    "x": "2027-03-01T00:00:00.000Z",
    "bev": 1101584,
    "total": 2948792
  },
  {
    "x": "2027-04-01T00:00:00.000Z",
    "bev": 1112467,
    "total": 2948843
  },
  {
    "x": "2027-05-01T00:00:00.000Z",
    "bev": 1123345,
    "total": 2948894
  },
  {
    "x": "2027-06-01T00:00:00.000Z",
    "bev": 1134218,
    "total": 2948945
  },
  {
    "x": "2027-07-01T00:00:00.000Z",
    "bev": 1145085,
    "total": 2948997
  },
  {
    "x": "2027-08-01T00:00:00.000Z",
    "bev": 1155946,
    "total": 2949050
  },
  {
    "x": "2027-09-01T00:00:00.000Z",
    "bev": 1166800,
    "total": 2949103
  },
  {
    "x": "2027-10-01T00:00:00.000Z",
    "bev": 1177647,
    "total": 2949157
  },
  {
    "x": "2027-11-01T00:00:00.000Z",
    "bev": 1188486,
    "total": 2949212
  },
  {
    "x": "2027-12-01T00:00:00.000Z",
    "bev": 1199318,
    "total": 2949267
  },
  {
    "x": "2028-01-01T00:00:00.000Z",
    "bev": 1210140,
    "total": 2949323
  },
  {
    "x": "2028-02-01T00:00:00.000Z",
    "bev": 1220953,
    "total": 2949379
  },
  {
    "x": "2028-03-01T00:00:00.000Z",
    "bev": 1231757,
    "total": 2949436
  },
  {
    "x": "2028-04-01T00:00:00.000Z",
    "bev": 1242551,
    "total": 2949493
  },
  {
    "x": "2028-05-01T00:00:00.000Z",
    "bev": 1253334,
    "total": 2949552
  },
  {
    "x": "2028-06-01T00:00:00.000Z",
    "bev": 1264106,
    "total": 2949611
  },
  {
    "x": "2028-07-01T00:00:00.000Z",
    "bev": 1274867,
    "total": 2949670
  },
  {
    "x": "2028-08-01T00:00:00.000Z",
    "bev": 1285616,
    "total": 2949730
  },
  {
    "x": "2028-09-01T00:00:00.000Z",
    "bev": 1296353,
    "total": 2949791
  },
  {
    "x": "2028-10-01T00:00:00.000Z",
    "bev": 1307077,
    "total": 2949853
  },
  {
    "x": "2028-11-01T00:00:00.000Z",
    "bev": 1317787,
    "total": 2949915
  },
  {
    "x": "2028-12-01T00:00:00.000Z",
    "bev": 1328485,
    "total": 2949978
  },
  {
    "x": "2029-01-01T00:00:00.000Z",
    "bev": 1339168,
    "total": 2950042
  },
  {
    "x": "2029-02-01T00:00:00.000Z",
    "bev": 1349837,
    "total": 2950107
  },
  {
    "x": "2029-03-01T00:00:00.000Z",
    "bev": 1360490,
    "total": 2950172
  },
  {
    "x": "2029-04-01T00:00:00.000Z",
    "bev": 1371129,
    "total": 2950238
  },
  {
    "x": "2029-05-01T00:00:00.000Z",
    "bev": 1381752,
    "total": 2950305
  },
  {
    "x": "2029-06-01T00:00:00.000Z",
    "bev": 1392358,
    "total": 2950372
  },
  {
    "x": "2029-07-01T00:00:00.000Z",
    "bev": 1402948,
    "total": 2950440
  },
  {
    "x": "2029-08-01T00:00:00.000Z",
    "bev": 1413521,
    "total": 2950509
  },
  {
    "x": "2029-09-01T00:00:00.000Z",
    "bev": 1424077,
    "total": 2950579
  },
  {
    "x": "2029-10-01T00:00:00.000Z",
    "bev": 1434615,
    "total": 2950649
  },
  {
    "x": "2029-11-01T00:00:00.000Z",
    "bev": 1445134,
    "total": 2950720
  },
  {
    "x": "2029-12-01T00:00:00.000Z",
    "bev": 1455635,
    "total": 2950792
  },
  {
    "x": "2030-01-01T00:00:00.000Z",
    "bev": 1466117,
    "total": 2950865
  },
  {
    "x": "2030-02-01T00:00:00.000Z",
    "bev": 1476579,
    "total": 2950938
  },
  {
    "x": "2030-03-01T00:00:00.000Z",
    "bev": 1487021,
    "total": 2951012
  },
  {
    "x": "2030-04-01T00:00:00.000Z",
    "bev": 1497442,
    "total": 2951087
  },
  {
    "x": "2030-05-01T00:00:00.000Z",
    "bev": 1507843,
    "total": 2951163
  },
  {
    "x": "2030-06-01T00:00:00.000Z",
    "bev": 1518222,
    "total": 2951239
  },
  {
    "x": "2030-07-01T00:00:00.000Z",
    "bev": 1528580,
    "total": 2951316
  },
  {
    "x": "2030-08-01T00:00:00.000Z",
    "bev": 1538916,
    "total": 2951394
  },
  {
    "x": "2030-09-01T00:00:00.000Z",
    "bev": 1549229,
    "total": 2951472
  },
  {
    "x": "2030-10-01T00:00:00.000Z",
    "bev": 1559518,
    "total": 2951552
  },
  {
    "x": "2030-11-01T00:00:00.000Z",
    "bev": 1569785,
    "total": 2951632
  },
  {
    "x": "2030-12-01T00:00:00.000Z",
    "bev": 1580027,
    "total": 2951712
  },
  {
    "x": "2031-01-01T00:00:00.000Z",
    "bev": 1590245,
    "total": 2951794
  },
  {
    "x": "2031-02-01T00:00:00.000Z",
    "bev": 1600439,
    "total": 2951876
  },
  {
    "x": "2031-03-01T00:00:00.000Z",
    "bev": 1610607,
    "total": 2951958
  },
  {
    "x": "2031-04-01T00:00:00.000Z",
    "bev": 1620749,
    "total": 2952042
  },
  {
    "x": "2031-05-01T00:00:00.000Z",
    "bev": 1630865,
    "total": 2952126
  },
  {
    "x": "2031-06-01T00:00:00.000Z",
    "bev": 1640954,
    "total": 2952210
  },
  {
    "x": "2031-07-01T00:00:00.000Z",
    "bev": 1651016,
    "total": 2952296
  },
  {
    "x": "2031-08-01T00:00:00.000Z",
    "bev": 1661051,
    "total": 2952382
  },
  {
    "x": "2031-09-01T00:00:00.000Z",
    "bev": 1671058,
    "total": 2952468
  },
  {
    "x": "2031-10-01T00:00:00.000Z",
    "bev": 1681036,
    "total": 2952555
  },
  {
    "x": "2031-11-01T00:00:00.000Z",
    "bev": 1690985,
    "total": 2952642
  },
  {
    "x": "2031-12-01T00:00:00.000Z",
    "bev": 1700905,
    "total": 2952731
  },
  {
    "x": "2032-01-01T00:00:00.000Z",
    "bev": 1710794,
    "total": 2952819
  },
  {
    "x": "2032-02-01T00:00:00.000Z",
    "bev": 1720654,
    "total": 2952908
  },
  {
    "x": "2032-03-01T00:00:00.000Z",
    "bev": 1730482,
    "total": 2952998
  },
  {
    "x": "2032-04-01T00:00:00.000Z",
    "bev": 1740279,
    "total": 2953087
  },
  {
    "x": "2032-05-01T00:00:00.000Z",
    "bev": 1750044,
    "total": 2953178
  },
  {
    "x": "2032-06-01T00:00:00.000Z",
    "bev": 1759777,
    "total": 2953268
  },
  {
    "x": "2032-07-01T00:00:00.000Z",
    "bev": 1769477,
    "total": 2953359
  },
  {
    "x": "2032-08-01T00:00:00.000Z",
    "bev": 1779144,
    "total": 2953451
  },
  {
    "x": "2032-09-01T00:00:00.000Z",
    "bev": 1788777,
    "total": 2953542
  },
  {
    "x": "2032-10-01T00:00:00.000Z",
    "bev": 1798375,
    "total": 2953634
  },
  {
    "x": "2032-11-01T00:00:00.000Z",
    "bev": 1807939,
    "total": 2953726
  },
  {
    "x": "2032-12-01T00:00:00.000Z",
    "bev": 1817467,
    "total": 2953818
  },
  {
    "x": "2033-01-01T00:00:00.000Z",
    "bev": 1826959,
    "total": 2953910
  },
  {
    "x": "2033-02-01T00:00:00.000Z",
    "bev": 1836415,
    "total": 2954002
  },
  {
    "x": "2033-03-01T00:00:00.000Z",
    "bev": 1845835,
    "total": 2954095
  },
  {
    "x": "2033-04-01T00:00:00.000Z",
    "bev": 1855217,
    "total": 2954187
  },
  {
    "x": "2033-05-01T00:00:00.000Z",
    "bev": 1864561,
    "total": 2954279
  },
  {
    "x": "2033-06-01T00:00:00.000Z",
    "bev": 1873866,
    "total": 2954371
  },
  {
    "x": "2033-07-01T00:00:00.000Z",
    "bev": 1883133,
    "total": 2954463
  },
  {
    "x": "2033-08-01T00:00:00.000Z",
    "bev": 1892360,
    "total": 2954554
  },
  {
    "x": "2033-09-01T00:00:00.000Z",
    "bev": 1901547,
    "total": 2954646
  },
  {
    "x": "2033-10-01T00:00:00.000Z",
    "bev": 1910694,
    "total": 2954737
  },
  {
    "x": "2033-11-01T00:00:00.000Z",
    "bev": 1919800,
    "total": 2954827
  },
  {
    "x": "2033-12-01T00:00:00.000Z",
    "bev": 1928865,
    "total": 2954917
  },
  {
    "x": "2034-01-01T00:00:00.000Z",
    "bev": 1937887,
    "total": 2955007
  },
  {
    "x": "2034-02-01T00:00:00.000Z",
    "bev": 1946867,
    "total": 2955096
  },
  {
    "x": "2034-03-01T00:00:00.000Z",
    "bev": 1955804,
    "total": 2955184
  },
  {
    "x": "2034-04-01T00:00:00.000Z",
    "bev": 1964697,
    "total": 2955272
  },
  {
    "x": "2034-05-01T00:00:00.000Z",
    "bev": 1973547,
    "total": 2955359
  },
  {
    "x": "2034-06-01T00:00:00.000Z",
    "bev": 1982351,
    "total": 2955445
  },
  {
    "x": "2034-07-01T00:00:00.000Z",
    "bev": 1991111,
    "total": 2955530
  },
  {
    "x": "2034-08-01T00:00:00.000Z",
    "bev": 1999825,
    "total": 2955614
  },
  {
    "x": "2034-09-01T00:00:00.000Z",
    "bev": 2008492,
    "total": 2955697
  },
  {
    "x": "2034-10-01T00:00:00.000Z",
    "bev": 2017113,
    "total": 2955779
  },
  {
    "x": "2034-11-01T00:00:00.000Z",
    "bev": 2025687,
    "total": 2955859
  },
  {
    "x": "2034-12-01T00:00:00.000Z",
    "bev": 2034213,
    "total": 2955939
  },
  {
    "x": "2035-01-01T00:00:00.000Z",
    "bev": 2042691,
    "total": 2956017
  },
  {
    "x": "2035-02-01T00:00:00.000Z",
    "bev": 2051121,
    "total": 2956093
  },
  {
    "x": "2035-03-01T00:00:00.000Z",
    "bev": 2059501,
    "total": 2956168
  },
  {
    "x": "2035-04-01T00:00:00.000Z",
    "bev": 2067831,
    "total": 2956241
  },
  {
    "x": "2035-05-01T00:00:00.000Z",
    "bev": 2076111,
    "total": 2956312
  },
  {
    "x": "2035-06-01T00:00:00.000Z",
    "bev": 2084341,
    "total": 2956382
  },
  {
    "x": "2035-07-01T00:00:00.000Z",
    "bev": 2092519,
    "total": 2956450
  },
  {
    "x": "2035-08-01T00:00:00.000Z",
    "bev": 2100645,
    "total": 2956515
  },
  {
    "x": "2035-09-01T00:00:00.000Z",
    "bev": 2108720,
    "total": 2956579
  },
  {
    "x": "2035-10-01T00:00:00.000Z",
    "bev": 2116741,
    "total": 2956640
  },
  {
    "x": "2035-11-01T00:00:00.000Z",
    "bev": 2124710,
    "total": 2956700
  },
  {
    "x": "2035-12-01T00:00:00.000Z",
    "bev": 2132625,
    "total": 2956756
  },
  {
    "x": "2036-01-01T00:00:00.000Z",
    "bev": 2140486,
    "total": 2956811
  },
  {
    "x": "2036-02-01T00:00:00.000Z",
    "bev": 2148292,
    "total": 2956863
  },
  {
    "x": "2036-03-01T00:00:00.000Z",
    "bev": 2156043,
    "total": 2956912
  },
  {
    "x": "2036-04-01T00:00:00.000Z",
    "bev": 2163739,
    "total": 2956958
  },
  {
    "x": "2036-05-01T00:00:00.000Z",
    "bev": 2171378,
    "total": 2957002
  },
  {
    "x": "2036-06-01T00:00:00.000Z",
    "bev": 2178962,
    "total": 2957042
  },
  {
    "x": "2036-07-01T00:00:00.000Z",
    "bev": 2186488,
    "total": 2957080
  },
  {
    "x": "2036-08-01T00:00:00.000Z",
    "bev": 2193958,
    "total": 2957115
  },
  {
    "x": "2036-09-01T00:00:00.000Z",
    "bev": 2201369,
    "total": 2957146
  },
  {
    "x": "2036-10-01T00:00:00.000Z",
    "bev": 2208723,
    "total": 2957174
  },
  {
    "x": "2036-11-01T00:00:00.000Z",
    "bev": 2216018,
    "total": 2957199
  },
  {
    "x": "2036-12-01T00:00:00.000Z",
    "bev": 2223254,
    "total": 2957221
  },
  {
    "x": "2037-01-01T00:00:00.000Z",
    "bev": 2230431,
    "total": 2957239
  },
  {
    "x": "2037-02-01T00:00:00.000Z",
    "bev": 2237548,
    "total": 2957253
  },
  {
    "x": "2037-03-01T00:00:00.000Z",
    "bev": 2244605,
    "total": 2957263
  },
  {
    "x": "2037-04-01T00:00:00.000Z",
    "bev": 2251602,
    "total": 2957270
  },
  {
    "x": "2037-05-01T00:00:00.000Z",
    "bev": 2258538,
    "total": 2957273
  },
  {
    "x": "2037-06-01T00:00:00.000Z",
    "bev": 2265412,
    "total": 2957273
  },
  {
    "x": "2037-07-01T00:00:00.000Z",
    "bev": 2272225,
    "total": 2957268
  },
  {
    "x": "2037-08-01T00:00:00.000Z",
    "bev": 2278976,
    "total": 2957259
  },
  {
    "x": "2037-09-01T00:00:00.000Z",
    "bev": 2285665,
    "total": 2957246
  },
  {
    "x": "2037-10-01T00:00:00.000Z",
    "bev": 2292292,
    "total": 2957229
  },
  {
    "x": "2037-11-01T00:00:00.000Z",
    "bev": 2298855,
    "total": 2957208
  },
  {
    "x": "2037-12-01T00:00:00.000Z",
    "bev": 2305356,
    "total": 2957183
  },
  {
    "x": "2038-01-01T00:00:00.000Z",
    "bev": 2311793,
    "total": 2957153
  },
  {
    "x": "2038-02-01T00:00:00.000Z",
    "bev": 2318166,
    "total": 2957119
  },
  {
    "x": "2038-03-01T00:00:00.000Z",
    "bev": 2324475,
    "total": 2957081
  },
  {
    "x": "2038-04-01T00:00:00.000Z",
    "bev": 2330720,
    "total": 2957038
  },
  {
    "x": "2038-05-01T00:00:00.000Z",
    "bev": 2336900,
    "total": 2956991
  },
  {
    "x": "2038-06-01T00:00:00.000Z",
    "bev": 2343016,
    "total": 2956939
  },
  {
    "x": "2038-07-01T00:00:00.000Z",
    "bev": 2349066,
    "total": 2956883
  },
  {
    "x": "2038-08-01T00:00:00.000Z",
    "bev": 2355052,
    "total": 2956823
  },
  {
    "x": "2038-09-01T00:00:00.000Z",
    "bev": 2360971,
    "total": 2956758
  },
  {
    "x": "2038-10-01T00:00:00.000Z",
    "bev": 2366825,
    "total": 2956689
  },
  {
    "x": "2038-11-01T00:00:00.000Z",
    "bev": 2372614,
    "total": 2956615
  },
  {
    "x": "2038-12-01T00:00:00.000Z",
    "bev": 2378336,
    "total": 2956537
  },
  {
    "x": "2039-01-01T00:00:00.000Z",
    "bev": 2383992,
    "total": 2956454
  },
  {
    "x": "2039-02-01T00:00:00.000Z",
    "bev": 2389581,
    "total": 2956367
  },
  {
    "x": "2039-03-01T00:00:00.000Z",
    "bev": 2395104,
    "total": 2956276
  },
  {
    "x": "2039-04-01T00:00:00.000Z",
    "bev": 2400561,
    "total": 2956180
  },
  {
    "x": "2039-05-01T00:00:00.000Z",
    "bev": 2405950,
    "total": 2956081
  },
  {
    "x": "2039-06-01T00:00:00.000Z",
    "bev": 2411273,
    "total": 2955977
  },
  {
    "x": "2039-07-01T00:00:00.000Z",
    "bev": 2416528,
    "total": 2955869
  },
  {
    "x": "2039-08-01T00:00:00.000Z",
    "bev": 2421717,
    "total": 2955757
  },
  {
    "x": "2039-09-01T00:00:00.000Z",
    "bev": 2426838,
    "total": 2955641
  },
  {
    "x": "2039-10-01T00:00:00.000Z",
    "bev": 2431892,
    "total": 2955521
  },
  {
    "x": "2039-11-01T00:00:00.000Z",
    "bev": 2436879,
    "total": 2955397
  },
  {
    "x": "2039-12-01T00:00:00.000Z",
    "bev": 2441798,
    "total": 2955270
  }
]