[
  {
    "x": "2022-01-01T00:00:00.000Z",
    "bev": 92,
    "total": 2457065
  },
  {
    "x": "2022-02-01T00:00:00.000Z",
    "bev": 227,
    "total": 2454948
  },
  {
    "x": "2022-03-01T00:00:00.000Z",
    "bev": 505,
    "total": 2452742
  },
  {
    "x": "2022-04-01T00:00:00.000Z",
    "bev": 734,
    "total": 2451411
  },
  {
    "x": "2022-05-01T00:00:00.000Z",
    "bev": 968,
    "total": 2452778
  },
  {
    "x": "2022-06-01T00:00:00.000Z",
    "bev": 1286,
    "total": 2453242
  },
  {
    "x": "2022-07-01T00:00:00.000Z",
    "bev": 1513,
    "total": 2453484
  },
  {
    "x": "2022-08-01T00:00:00.000Z",
    "bev": 1710,
    "total": 2451507
  },
  {
    "x": "2022-09-01T00:00:00.000Z",
    "bev": 1992,
    "total": 2449474
  },
  {
    "x": "2022-10-01T00:00:00.000Z",
    "bev": 2233,
    "total": 2446623
  },
  {
    "x": "2022-11-01T00:00:00.000Z",
    "bev": 2516,
    "total": 2444048
  },
  {
    "x": "2022-12-01T00:00:00.000Z",
    "bev": 2825,
    "total": 2439885
  },
  {
    "x": "2023-01-01T00:00:00.000Z",
    "bev": 3098,
    "total": 2439766
  },
  {
    "x": "2023-02-01T00:00:00.000Z",
    "bev": 3492,
    "total": 2439067
  },
  {
    "x": "2023-03-01T00:00:00.000Z",
    "bev": 4216,
    "total": 2441694
  },
  {
    "x": "2023-04-01T00:00:00.000Z",
    "bev": 4678,
    "total": 2441272
  },
  {
    "x": "2023-05-01T00:00:00.000Z",
    "bev": 5398,
    "total": 2443565
  },
  {
    "x": "2023-06-01T00:00:00.000Z",
    "bev": 6034,
    "total": 2446291
  },
  {
    "x": "2023-07-01T00:00:00.000Z",
    "bev": 6606,
    "total": 2448001
  },
  {
    "x": "2023-08-01T00:00:00.000Z",
    "bev": 7008,
    "total": 2447695
  },
  {
    "x": "2023-09-01T00:00:00.000Z",
    "bev": 7762,
    "total": 2448419
  },
  {
    "x": "2023-10-01T00:00:00.000Z",
    "bev": 8177,
    "total": 2449022
  },
  {
    "x": "2023-11-01T00:00:00.000Z",
    "bev": 8619,
    "total": 2448792
  },
  {
    "x": "2023-12-01T00:00:00.000Z",
    "bev": 9195,
    "total": 2446347
  },
  {
    "x": "2024-01-01T00:00:00.000Z",
    "bev": 9643,
    "total": 2448412
  },
  {
    "x": "2024-02-01T00:00:00.000Z",
    "bev": 10223,
    "total": 2449173
  },
  {
    "x": "2024-03-01T00:00:00.000Z",
    "bev": 10770,
    "total": 2450945
  },
  {
    "x": "2024-04-01T00:00:00.000Z",
    "bev": 11373,
    "total": 2453695
  },
  {
    "x": "2024-05-01T00:00:00.000Z",
    "bev": 11776,
    "total": 2456757
  },
  {
    "x": "2024-06-01T00:00:00.000Z",
    "bev": 12526,
    "total": 2460203
  },
  {
    "x": "2024-07-01T00:00:00.000Z",
    "bev": 13406,
    "total": 2461704
  },
  {
    "x": "2024-08-01T00:00:00.000Z",
    "bev": 13918,
    "total": 2459147
  },
  {
    "x": "2024-09-01T00:00:00.000Z",
    "bev": 14781,
    "total": 2458101
  },
  {
    "x": "2024-10-01T00:00:00.000Z",
    "bev": 15697,
    "total": 2457061
  },
  {
    "x": "2024-11-01T00:00:00.000Z",
    "bev": 16800,
    "total": 2457015
  },
  {
    "x": "2024-12-01T00:00:00.000Z",
    "bev": 17878,
    "total": 2455005
  },
  {
    "x": "2025-01-01T00:00:00.000Z",
    "bev": 18402,
    "total": 2454948
  },
  {
    "x": "2025-02-01T00:00:00.000Z",
    "bev": 19117,
    "total": 2454048
  },
  {
    "x": "2025-03-01T00:00:00.000Z",
    "bev": 19889,
    "total": 2456047
  },
  {
    "x": "2025-04-01T00:00:00.000Z",
    "bev": 20516,
    "total": 2459974
  },
  {
    "x": "2025-05-01T00:00:00.000Z",
    "bev": 21259,
    "total": 2464920
  },
  {
    "x": "2025-06-01T00:00:00.000Z",
    "bev": 22124,
    "total": 2468841
  },
  {
    "x": "2025-07-01T00:00:00.000Z",
    "bev": 22731,
    "total": 2471718
  },
  {
    "x": "2025-08-01T00:00:00.000Z",
    "bev": 23155,
    "total": 2469178
  },
  {
    "x": "2025-09-01T00:00:00.000Z",
    "bev": 24001,
    "total": 2470718
  },
  {
    "x": "2025-10-01T00:00:00.000Z",
    "bev": 24796,
    "total": 2470747
  },
  {
    "x": "2025-11-01T00:00:00.000Z",
    "bev": 25581,
    "total": 2470469
  },
  {
    "x": "2025-12-01T00:00:00.000Z",
    "bev": 26726,
    "total": 2470477
  },
  {
    "x": "2026-01-01T00:00:00.000Z",
    "bev": 27354,
    "total": 2469825
  },
  {
    "x": "2026-02-01T00:00:00.000Z",
    "bev": 27995,
    "total": 2469099
  },
  {
    "x": "2026-03-01T00:00:00.000Z",
    "bev": 28922,
    "total": 2469179
  },
  {
    "x": "2026-04-01T00:00:00.000Z",
    "bev": 29869,
    "total": 2469258
  },
  {
    "x": "2026-05-01T00:00:00.000Z",
    "bev": 30836,
    "total": 2469336
  },
  {
    "x": "2026-06-01T00:00:00.000Z",
    "bev": 31823,
    "total": 2469412
  },
  {
    "x": "2026-07-01T00:00:00.000Z",
    "bev": 32830,
    "total": 2469487
  },
  {
    "x": "2026-08-01T00:00:00.000Z",
    "bev": 33859,
    "total": 2469560
  },
  {
    "x": "2026-09-01T00:00:00.000Z",
    "bev": 34909,
    "total": 2469632
  },
  {
    "x": "2026-10-01T00:00:00.000Z",
    "bev": 35980,
    "total": 2469703
  },
  {
    "x": "2026-11-01T00:00:00.000Z",
    "bev": 37074,
    "total": 2469772
  },
  {
    "x": "2026-12-01T00:00:00.000Z",
    "bev": 38190,
    "total": 2469840
  },
  {
    "x": "2027-01-01T00:00:00.000Z",
    "bev": 39330,
    "total": 2469907
  },
  {
    "x": "2027-02-01T00:00:00.000Z",
    "bev": 40492,
    "total": 2469972
  },
  {
    "x": "2027-03-01T00:00:00.000Z",
    "bev": 41679,
    "total": 2470037
  },
  {
    "x": "2027-04-01T00:00:00.000Z",
    "bev": 42889,
    "total": 2470100
  },
  {
    "x": "2027-05-01T00:00:00.000Z",
    "bev": 44124,
    "total": 2470162
  },
  {
    "x": "2027-06-01T00:00:00.000Z",
    "bev": 45384,
    "total": 2470223
  },
  {
    "x": "2027-07-01T00:00:00.000Z",
    "bev": 46670,
    "total": 2470282
  },
  {
    "x": "2027-08-01T00:00:00.000Z",
    "bev": 47981,
    "total": 2470341
  },
  {
    "x": "2027-09-01T00:00:00.000Z",
    "bev": 49319,
    "total": 2470399
  },
  {
    "x": "2027-10-01T00:00:00.000Z",
    "bev": 50683,
    "total": 2470456
  },
  {
    "x": "2027-11-01T00:00:00.000Z",
    "bev": 52074,
    "total": 2470511
  },
  {
    "x": "2027-12-01T00:00:00.000Z",
    "bev": 53494,
    "total": 2470566
  },
  {
    "x": "2028-01-01T00:00:00.000Z",
    "bev": 54941,
    "total": 2470620
  },
  {
    "x": "2028-02-01T00:00:00.000Z",
    "bev": 56417,
    "total": 2470672
  },
  {
    "x": "2028-03-01T00:00:00.000Z",
    "bev": 57921,
    "total": 2470724
  },
  {
    "x": "2028-04-01T00:00:00.000Z",
    "bev": 59456,
    "total": 2470775
  },
  {
    "x": "2028-05-01T00:00:00.000Z",
    "bev": 61020,
    "total": 2470825
  },
  {
    "x": "2028-06-01T00:00:00.000Z",
    "bev": 62614,
    "total": 2470875
  },
  {
    "x": "2028-07-01T00:00:00.000Z",
    "bev": 64240,
    "total": 2470923
  },
  {
    "x": "2028-08-01T00:00:00.000Z",
    "bev": 65897,
    "total": 2470971
  },
  {
    "x": "2028-09-01T00:00:00.000Z",
    "bev": 67585,
    "total": 2471018
  },
  {
    "x": "2028-10-01T00:00:00.000Z",
    "bev": 69306,
    "total": 2471064
  },
  {
    "x": "2028-11-01T00:00:00.000Z",
    "bev": 71059,
    "total": 2471109
  },
  {
    "x": "2028-12-01T00:00:00.000Z",
    "bev": 72846,
    "total": 2471154
  },
  {
    "x": "2029-01-01T00:00:00.000Z",
    "bev": 74667,
    "total": 2471197
  },
  {
    "x": "2029-02-01T00:00:00.000Z",
    "bev": 76521,
    "total": 2471241
  },
  {
    "x": "2029-03-01T00:00:00.000Z",
    "bev": 78411,
    "total": 2471283
  },
  {
    "x": "2029-04-01T00:00:00.000Z",
    "bev": 80335,
    "total": 2471325
  },
  {
    "x": "2029-05-01T00:00:00.000Z",
    "bev": 82295,
    "total": 2471366
  },
  {
    "x": "2029-06-01T00:00:00.000Z",
    "bev": 84291,
    "total": 2471407
  },
  {
    "x": "2029-07-01T00:00:00.000Z",
    "bev": 86324,
    "total": 2471446
  },
  {
    "x": "2029-08-01T00:00:00.000Z",
    "bev": 88394,
    "total": 2471486
  },
  {
    "x": "2029-09-01T00:00:00.000Z",
    "bev": 90502,
    "total": 2471525
  },
  {
    "x": "2029-10-01T00:00:00.000Z",
    "bev": 92647,
    "total": 2471563
  },
  {
    "x": "2029-11-01T00:00:00.000Z",
    "bev": 94832,
    "total": 2471600
  },
  {
    "x": "2029-12-01T00:00:00.000Z",
    "bev": 97055,
    "total": 2471637
  },
  {
    "x": "2030-01-01T00:00:00.000Z",
    "bev": 99318,
    "total": 2471674
  },
  {
    "x": "2030-02-01T00:00:00.000Z",
    "bev": 101620,
    "total": 2471710
  },
  {
    "x": "2030-03-01T00:00:00.000Z",
    "bev": 103963,
    "total": 2471746
  },
  {
    "x": "2030-04-01T00:00:00.000Z",
    "bev": 106347,
    "total": 2471781
  },
  {
    "x": "2030-05-01T00:00:00.000Z",
    "bev": 108773,
    "total": 2471815
  },
  {
    "x": "2030-06-01T00:00:00.000Z",
    "bev": 111240,
    "total": 2471849
  },
  {
    "x": "2030-07-01T00:00:00.000Z",
    "bev": 113750,
    "total": 2471883
  },
  {
    "x": "2030-08-01T00:00:00.000Z",
    "bev": 116302,
    "total": 2471917
  },
  {
    "x": "2030-09-01T00:00:00.000Z",
    "bev": 118898,
    "total": 2471949
  },
  {
    "x": "2030-10-01T00:00:00.000Z",
    "bev": 121537,
    "total": 2471982
  },
  {
    "x": "2030-11-01T00:00:00.000Z",
    "bev": 124221,
    "total": 2472014
  },
  {
    "x": "2030-12-01T00:00:00.000Z",
    "bev": 126949,
    "total": 2472046
  },
  {
    "x": "2031-01-01T00:00:00.000Z",
    "bev": 129722,
    "total": 2472077
  },
  {
    "x": "2031-02-01T00:00:00.000Z",
    "bev": 132541,
    "total": 2472108
  },
  {
    "x": "2031-03-01T00:00:00.000Z",
    "bev": 135405,
    "total": 2472139
  },
  {
    "x": "2031-04-01T00:00:00.000Z",
    "bev": 138316,
    "total": 2472169
  },
  {
    "x": "2031-05-01T00:00:00.000Z",
    "bev": 141273,
    "total": 2472199
  },
  {
    "x": "2031-06-01T00:00:00.000Z",
    "bev": 144278,
    "total": 2472229
  },
  {
    "x": "2031-07-01T00:00:00.000Z",
    "bev": 147329,
    "total": 2472259
  },
  {
    "x": "2031-08-01T00:00:00.000Z",
    "bev": 150429,
    "total": 2472288
  },
  {
    "x": "2031-09-01T00:00:00.000Z",
    "bev": 153577,
    "total": 2472317
  },
  {
    "x": "2031-10-01T00:00:00.000Z",
    "bev": 156774,
    "total": 2472346
  },
  {
    "x": "2031-11-01T00:00:00.000Z",
    "bev": 160019,
    "total": 2472374
  },
  {
    "x": "2031-12-01T00:00:00.000Z",
    "bev": 163314,
    "total": 2472402
  },
  {
    "x": "2032-01-01T00:00:00.000Z",
    "bev": 166658,
    "total": 2472430
  },
  {
    "x": "2032-02-01T00:00:00.000Z",
    "bev": 170053,
    "total": 2472458
  },
  {
    "x": "2032-03-01T00:00:00.000Z",
    "bev": 173497,
    "total": 2472486
  },
  {
    "x": "2032-04-01T00:00:00.000Z",
    "bev": 176993,
    "total": 2472513
  },
  {
    "x": "2032-05-01T00:00:00.000Z",
    "bev": 180539,
    "total": 2472540
  },
  {
    "x": "2032-06-01T00:00:00.000Z",
    "bev": 184136,
    "total": 2472567
  },
  {
    "x": "2032-07-01T00:00:00.000Z",
    "bev": 187784,
    "total": 2472594
  },
  {
    "x": "2032-08-01T00:00:00.000Z",
    "bev": 191485,
    "total": 2472621
  },
  {
    "x": "2032-09-01T00:00:00.000Z",
    "bev": 195237,
    "total": 2472648
  },
  {
    "x": "2032-10-01T00:00:00.000Z",
    "bev": 199041,
    "total": 2472674
  },
  {
    "x": "2032-11-01T00:00:00.000Z",
    "bev": 202898,
    "total": 2472701
  },
  {
    "x": "2032-12-01T00:00:00.000Z",
    "bev": 206807,
    "total": 2472727
  },
  {
    "x": "2033-01-01T00:00:00.000Z",
    "bev": 210769,
    "total": 2472753
  },
  {
    "x": "2033-02-01T00:00:00.000Z",
    "bev": 214784,
    "total": 2472779
  },
  {
    "x": "2033-03-01T00:00:00.000Z",
    "bev": 218852,
    "total": 2472805
  },
  {
    "x": "2033-04-01T00:00:00.000Z",
    "bev": 222973,
    "total": 2472831
  },
  {
    "x": "2033-05-01T00:00:00.000Z",
    "bev": 227148,
    "total": 2472857
  },
  {
    "x": "2033-06-01T00:00:00.000Z",
    "bev": 231376,
    "total": 2472883
  },
  {
    "x": "2033-07-01T00:00:00.000Z",
    "bev": 235657,
    "total": 2472908
  },
  {
    "x": "2033-08-01T00:00:00.000Z",
    "bev": 239993,
    "total": 2472934
  },
  {
    "x": "2033-09-01T00:00:00.000Z",
    "bev": 244382,
    "total": 2472960
  },
  {
    "x": "2033-10-01T00:00:00.000Z",
    "bev": 248824,
    "total": 2472985
  },
  {
    "x": "2033-11-01T00:00:00.000Z",
    "bev": 253321,
    "total": 2473011
  },
  {
    "x": "2033-12-01T00:00:00.000Z",
    "bev": 257872,
    "total": 2473037
  },
  {
    "x": "2034-01-01T00:00:00.000Z",
    "bev": 262476,
    "total": 2473062
  },
  {
    "x": "2034-02-01T00:00:00.000Z",
    "bev": 267134,
    "total": 2473088
  },
  {
    "x": "2034-03-01T00:00:00.000Z",
    "bev": 271846,
    "total": 2473114
  },
  {
    "x": "2034-04-01T00:00:00.000Z",
    "bev": 276612,
    "total": 2473140
  },
  {
    "x": "2034-05-01T00:00:00.000Z",
    "bev": 281432,
    "total": 2473165
  },
  {
    "x": "2034-06-01T00:00:00.000Z",
    "bev": 286305,
    "total": 2473191
  },
  {
    "x": "2034-07-01T00:00:00.000Z",
    "bev": 291232,
    "total": 2473217
  },
  {
    "x": "2034-08-01T00:00:00.000Z",
    "bev": 296212,
    "total": 2473243
  },
  {
    "x": "2034-09-01T00:00:00.000Z",
    "bev": 301246,
    "total": 2473269
  },
  {
    "x": "2034-10-01T00:00:00.000Z",
    "bev": 306333,
    "total": 2473295
  },
  {
    "x": "2034-11-01T00:00:00.000Z",
    "bev": 311473,
    "total": 2473321
  },
  {
    "x": "2034-12-01T00:00:00.000Z",
    "bev": 316666,
    "total": 2473347
  },
  {
    "x": "2035-01-01T00:00:00.000Z",
    "bev": 321912,
    "total": 2473374
  },
  {
    "x": "2035-02-01T00:00:00.000Z",
    "bev": 327210,
    "total": 2473400
  },
  {
    "x": "2035-03-01T00:00:00.000Z",
    "bev": 332560,
    "total": 2473426
  },
  {
    "x": "2035-04-01T00:00:00.000Z",
    "bev": 337963,
    "total": 2473453
  },
  {
    "x": "2035-05-01T00:00:00.000Z",
    "bev": 343417,
    "total": 2473480
  },
  {
    "x": "2035-06-01T00:00:00.000Z",
    "bev": 348923,
    "total": 2473507
  },
  {
    "x": "2035-07-01T00:00:00.000Z",
    "bev": 354480,
    "total": 2473534
  },
  {
    "x": "2035-08-01T00:00:00.000Z",
    "bev": 360088,
    "total": 2473561
  },
  {
    "x": "2035-09-01T00:00:00.000Z",
    "bev": 365747,
    "total": 2473588
  },
  {
    "x": "2035-10-01T00:00:00.000Z",
    "bev": 371457,
    "total": 2473616
  },
  {
    "x": "2035-11-01T00:00:00.000Z",
    "bev": 377216,
    "total": 2473643
  },
  {
    "x": "2035-12-01T00:00:00.000Z",
    "bev": 383025,
    "total": 2473671
  },
  {
    "x": "2036-01-01T00:00:00.000Z",
    "bev": 388883,
    "total": 2473699
  },
  {
    "x": "2036-02-01T00:00:00.000Z",
    "bev": 394791,
    "total": 2473727
  },
  {
    "x": "2036-03-01T00:00:00.000Z",
    "bev": 400747,
    "total": 2473756
  },
  {
    "x": "2036-04-01T00:00:00.000Z",
    "bev": 406751,
    "total": 2473784
  },
  {
    "x": "2036-05-01T00:00:00.000Z",
    "bev": 412802,
    "total": 2473813
  },
  {
    "x": "2036-06-01T00:00:00.000Z",
    "bev": 418902,
    "total": 2473842
  },
  {
    "x": "2036-07-01T00:00:00.000Z",
    "bev": 425048,
    "total": 2473871
  },
  {
    "x": "2036-08-01T00:00:00.000Z",
    "bev": 431240,
    "total": 2473900
  },
  {
    "x": "2036-09-01T00:00:00.000Z",
    "bev": 437479,
    "total": 2473929
  },
  {
    "x": "2036-10-01T00:00:00.000Z",
    "bev": 443763,
    "total": 2473959
  },
  {
    "x": "2036-11-01T00:00:00.000Z",
    "bev": 450092,
    "total": 2473989
  },
  {
    "x": "2036-12-01T00:00:00.000Z",
    "bev": 456466,
    "total": 2474019
  },
  {
    "x": "2037-01-01T00:00:00.000Z",
    "bev": 462884,
    "total": 2474050
  },
  {
    "x": "2037-02-01T00:00:00.000Z",
    "bev": 469345,
    "total": 2474080
  },
  {
    "x": "2037-03-01T00:00:00.000Z",
    "bev": 475850,
    "total": 2474111
  },
  {
    "x": "2037-04-01T00:00:00.000Z",
    "bev": 482396,
    "total": 2474142
  },
  {
    "x": "2037-05-01T00:00:00.000Z",
    "bev": 488985,
    "total": 2474173
  },
  {
    "x": "2037-06-01T00:00:00.000Z",
    "bev": 495616,
    "total": 2474205
  },
  {
    "x": "2037-07-01T00:00:00.000Z",
    "bev": 502287,
    "total": 2474236
  },
  {
    "x": "2037-08-01T00:00:00.000Z",
    "bev": 508998,
    "total": 2474268
  },
  {
    "x": "2037-09-01T00:00:00.000Z",
    "bev": 515750,
    "total": 2474301
  },
  {
    "x": "2037-10-01T00:00:00.000Z",
    "bev": 522540,
    "total": 2474333
  },
  {
    "x": "2037-11-01T00:00:00.000Z",
    "bev": 529369,
    "total": 2474366
  },
  {
    "x": "2037-12-01T00:00:00.000Z",
    "bev": 536236,
    "total": 2474399
  },
  {
    "x": "2038-01-01T00:00:00.000Z",
    "bev": 543140,
    "total": 2474432
  },
  {
    "x": "2038-02-01T00:00:00.000Z",
    "bev": 550082,
    "total": 2474465
  },
  {
    "x": "2038-03-01T00:00:00.000Z",
    "bev": 557059,
    "total": 2474499
  },
  {
    "x": "2038-04-01T00:00:00.000Z",
    "bev": 564072,
    "total": 2474533
  },
  {
    "x": "2038-05-01T00:00:00.000Z",
    "bev": 571120,
    "total": 2474567
  },
  {
    "x": "2038-06-01T00:00:00.000Z",
    "bev": 578203,
    "total": 2474601
  },
  {
    "x": "2038-07-01T00:00:00.000Z",
    "bev": 585319,
    "total": 2474636
  },
  {
    "x": "2038-08-01T00:00:00.000Z",
    "bev": 592468,
    "total": 2474671
  },
  {
    "x": "2038-09-01T00:00:00.000Z",
    "bev": 599650,
    "total": 2474706
  },
  {
    "x": "2038-10-01T00:00:00.000Z",
    "bev": 606864,
    "total": 2474741
  },
  {
    "x": "2038-11-01T00:00:00.000Z",
    "bev": 614109,
    "total": 2474776
  },
  {
    "x": "2038-12-01T00:00:00.000Z",
    "bev": 621385,
    "total": 2474812
  },
  {
    "x": "2039-01-01T00:00:00.000Z",
    "bev": 628690,
    "total": 2474848
  },
  {
    "x": "2039-02-01T00:00:00.000Z",
    "bev": 636025,
    "total": 2474884
  },
  {
    "x": "2039-03-01T00:00:00.000Z",
    "bev": 643389,
    "total": 2474920
  },
  {
    "x": "2039-04-01T00:00:00.000Z",
    "bev": 650780,
    "total": 2474957
  },
  {
    "x": "2039-05-01T00:00:00.000Z",
    "bev": 658199,
    "total": 2474994
  },
  {
    "x": "2039-06-01T00:00:00.000Z",
    "bev": 665645,
    "total": 2475030
  },
  {
    "x": "2039-07-01T00:00:00.000Z",
    "bev": 673117,
    "total": 2475067
  },
  {
    "x": "2039-08-01T00:00:00.000Z",
    "bev": 680614,
    "total": 2475105
  },
  {
    "x": "2039-09-01T00:00:00.000Z",
    "bev": 688137,
    "total": 2475142
  },
  {
    "x": "2039-10-01T00:00:00.000Z",
    "bev": 695683,
    "total": 2475179
  },
  {
    "x": "2039-11-01T00:00:00.000Z",
    "bev": 703253,
    "total": 2475217
  },
  {
    "x": "2039-12-01T00:00:00.000Z",
    "bev": 710846,
    "total": 2475255
  }
]