[
  {
    "x": "2022-01-01T00:00:00.000Z",
    "bev": 401,
    "total": 880716
  },
  {
    "x": "2022-02-01T00:00:00.000Z",
    "bev": 898,
    "total": 880627
  },
  {
    "x": "2022-03-01T00:00:00.000Z",
    "bev": 1615,
    "total": 881165
  },
  {
    "x": "2022-04-01T00:00:00.000Z",
    "bev": 2095,
    "total": 880705
  },
  {
    "x": "2022-05-01T00:00:00.000Z",
    "bev": 2728,
    "total": 880436
  },
  {
    "x": "2022-06-01T00:00:00.000Z",
    "bev": 3210,
    "total": 880222
  },
  {
    "x": "2022-07-01T00:00:00.000Z",
    "bev": 3643,
    "total": 880138
  },
  {
    "x": "2022-08-01T00:00:00.000Z",
    "bev": 3992,
    "total": 879299
  },
  {
    "x": "2022-09-01T00:00:00.000Z",
    "bev": 4589,
    "total": 879063
  },
  {
    "x": "2022-10-01T00:00:00.000Z",
    "bev": 5118,
    "total": 878719
  },
  {
    "x": "2022-11-01T00:00:00.000Z",
    "bev": 5786,
    "total": 878344
  },
  {
    "x": "2022-12-01T00:00:00.000Z",
    "bev": 6389,
    "total": 877653
  },
  {
    "x": "2023-01-01T00:00:00.000Z",
    "bev": 7062,
    "total": 877566
  },
  {
    "x": "2023-02-01T00:00:00.000Z",
    "bev": 7856,
    "total": 877929
  },
  {
    "x": "2023-03-01T00:00:00.000Z",
    "bev": 8899,
    "total": 879360
  },
  {
    "x": "2023-04-01T00:00:00.000Z",
    "bev": 9662,
    "total": 879720
  },
  {
    "x": "2023-05-01T00:00:00.000Z",
    "bev": 10572,
    "total": 880304
  },
  {
    "x": "2023-06-01T00:00:00.000Z",
    "bev": 11666,
    "total": 881253
  },
  {
    "x": "2023-07-01T00:00:00.000Z",
    "bev": 12570,
    "total": 881641
  },
  {
    "x": "2023-08-01T00:00:00.000Z",
    "bev": 13492,
    "total": 881236
  },
  {
    "x": "2023-09-01T00:00:00.000Z",
    "bev": 14499,
    "total": 881293
  },
  {
    "x": "2023-10-01T00:00:00.000Z",
    "bev": 15757,
    "total": 881638
  },
  {
    "x": "2023-11-01T00:00:00.000Z",
    "bev": 16606,
    "total": 881506
  },
  {
    "x": "2023-12-01T00:00:00.000Z",
    "bev": 17402,
    "total": 880924
  },
  {
    "x": "2024-01-01T00:00:00.000Z",
    "bev": 18179,
    "total": 880735
  },
  {
    "x": "2024-02-01T00:00:00.000Z",
    "bev": 19118,
    "total": 881195
  },
  {
    "x": "2024-03-01T00:00:00.000Z",
    "bev": 20359,
    "total": 881955
  },
  {
    "x": "2024-04-01T00:00:00.000Z",
    "bev": 21610,
    "total": 882539
  },
  {
    "x": "2024-05-01T00:00:00.000Z",
    "bev": 22596,
    "total": 882557
  },
  {
    "x": "2024-06-01T00:00:00.000Z",
    "bev": 23819,
    "total": 883050
  },
  {
    "x": "2024-07-01T00:00:00.000Z",
    "bev": 25070,
    "total": 883508
  },
  {
    "x": "2024-08-01T00:00:00.000Z",
    "bev": 25939,
    "total": 882587
  },
  {
    "x": "2024-09-01T00:00:00.000Z",
    "bev": 27051,
    "total": 882372
  },
  {
    "x": "2024-10-01T00:00:00.000Z",
    "bev": 28355,
    "total": 882712
  },
  {
    "x": "2024-11-01T00:00:00.000Z",
    "bev": 29261,
    "total": 882332
  },
  {
    "x": "2024-12-01T00:00:00.000Z",
    "bev": 30135,
    "total": 881611
  },
  {
    "x": "2025-01-01T00:00:00.000Z",
    "bev": 31297,
    "total": 881493
  },
  {
    "x": "2025-02-01T00:00:00.000Z",
    "bev": 32426,
    "total": 881767
  },
  {
    "x": "2025-03-01T00:00:00.000Z",
    "bev": 33852,
    "total": 882769
  },
  {
    "x": "2025-04-01T00:00:00.000Z",
    "bev": 34845,
    "total": 883295
  },
  {
    "x": "2025-05-01T00:00:00.000Z",
    "bev": 35727,
    "total": 883514
  },
  {
    "x": "2025-06-01T00:00:00.000Z",
    "bev": 36660,
    "total": 883842
  },
  {
    "x": "2025-07-01T00:00:00.000Z",
    "bev": 37531,
    "total": 884516
  },
  {
    "x": "2025-08-01T00:00:00.000Z",
    "bev": 38239,
    "total": 883617
  },
  {
    "x": "2025-09-01T00:00:00.000Z",
    "bev": 39477,
    "total": 883554
  },
  {
    "x": "2025-10-01T00:00:00.000Z",
    "bev": 40392,
    "total": 883511
  },
  {
    "x": "2025-11-01T00:00:00.000Z",
    "bev": 41514,
    "total": 883150
  },
  {
    "x": "2025-12-01T00:00:00.000Z",
    "bev": 42721,
    "total": 882692
  },
  {
    "x": "2026-01-01T00:00:00.000Z",
    "bev": 43688,
    "total": 882187
  },
  {
    "x": "2026-02-01T00:00:00.000Z",
    "bev": 44702,
    "total": 882742
  },
  {
    "x": "2026-03-01T00:00:00.000Z",
    "bev": 46077,
    "total": 883696
  },
  {
    "x": "2026-04-01T00:00:00.000Z",
    "bev": 47314,
    "total": 883724
  },
  {
    "x": "2026-05-01T00:00:00.000Z",
    "bev": 48565,
    "total": 883751
  },
  {
    "x": "2026-06-01T00:00:00.000Z",
    "bev": 49831,
    "total": 883777
  },
  {
    "x": "2026-07-01T00:00:00.000Z",
    "bev": 51110,
    "total": 883803
  },
  {
    "x": "2026-08-01T00:00:00.000Z",
    "bev": 52405,
    "total": 883829
  },
  {
    "x": "2026-09-01T00:00:00.000Z",
    "bev": 53714,
    "total": 883854
  },
  {
    "x": "2026-10-01T00:00:00.000Z",
    "bev": 55037,
    "total": 883878
  },
  {
    "x": "2026-11-01T00:00:00.000Z",
    "bev": 56375,
    "total": 883902
  },
  {
    "x": "2026-12-01T00:00:00.000Z",
    "bev": 57727,
    "total": 883926
  },
  {
    "x": "2027-01-01T00:00:00.000Z",
    "bev": 59095,
    "total": 883949
  },
  {
    "x": "2027-02-01T00:00:00.000Z",
    "bev": 60477,
    "total": 883972
  },
  {
    "x": "2027-03-01T00:00:00.000Z",
    "bev": 61873,
    "total": 883994
  },
  {
    "x": "2027-04-01T00:00:00.000Z",
    "bev": 63285,
    "total": 884016
  },
  {
    "x": "2027-05-01T00:00:00.000Z",
    "bev": 64712,
    "total": 884037
  },
  {
    "x": "2027-06-01T00:00:00.000Z",
    "bev": 66153,
    "total": 884058
  },
  {
    "x": "2027-07-01T00:00:00.000Z",
    "bev": 67609,
    "total": 884079
  },
  {
    "x": "2027-08-01T00:00:00.000Z",
    "bev": 69081,
    "total": 884099
  },
  {
    "x": "2027-09-01T00:00:00.000Z",
    "bev": 70567,
    "total": 884118
  },
  {
    "x": "2027-10-01T00:00:00.000Z",
    "bev": 72068,
    "total": 884138
  },
  {
    "x": "2027-11-01T00:00:00.000Z",
    "bev": 73585,
    "total": 884157
  },
  {
    "x": "2027-12-01T00:00:00.000Z",
    "bev": 75116,
    "total": 884175
  },
  {
    "x": "2028-01-01T00:00:00.000Z",
    "bev": 76663,
    "total": 884194
  },
  {
    "x": "2028-02-01T00:00:00.000Z",
    "bev": 78225,
    "total": 884212
  },
  {
    "x": "2028-03-01T00:00:00.000Z",
    "bev": 79802,
    "total": 884229
  },
  {
    "x": "2028-04-01T00:00:00.000Z",
    "bev": 81394,
    "total": 884246
  },
  {
    "x": "2028-05-01T00:00:00.000Z",
    "bev": 83001,
    "total": 884263
  },
  {
    "x": "2028-06-01T00:00:00.000Z",
    "bev": 84623,
    "total": 884280
  },
  {
    "x": "2028-07-01T00:00:00.000Z",
    "bev": 86261,
    "total": 884296
  },
  {
    "x": "2028-08-01T00:00:00.000Z",
    "bev": 87913,
    "total": 884312
  },
  {
    "x": "2028-09-01T00:00:00.000Z",
    "bev": 89581,
    "total": 884328
  },
  {
    "x": "2028-10-01T00:00:00.000Z",
    "bev": 91264,
    "total": 884343
  },
  {
    "x": "2028-11-01T00:00:00.000Z",
    "bev": 92962,
    "total": 884358
  },
  {
    "x": "2028-12-01T00:00:00.000Z",
    "bev": 94675,
    "total": 884373
  },
  {
    "x": "2029-01-01T00:00:00.000Z",
    "bev": 96403,
    "total": 884387
  },
  {
    "x": "2029-02-01T00:00:00.000Z",
    "bev": 98147,
    "total": 884401
  },
  {
    "x": "2029-03-01T00:00:00.000Z",
    "bev": 99905,
    "total": 884415
  },
  {
    "x": "2029-04-01T00:00:00.000Z",
    "bev": 101679,
    "total": 884429
  },
  {
    "x": "2029-05-01T00:00:00.000Z",
    "bev": 103467,
    "total": 884442
  },
  {
    "x": "2029-06-01T00:00:00.000Z",
    "bev": 105271,
    "total": 884455
  },
  {
    "x": "2029-07-01T00:00:00.000Z",
    "bev": 107090,
    "total": 884468
  },
  {
    "x": "2029-08-01T00:00:00.000Z",
    "bev": 108923,
    "total": 884481
  },
  {
    "x": "2029-09-01T00:00:00.000Z",
    "bev": 110771,
    "total": 884493
  },
  {
    "x": "2029-10-01T00:00:00.000Z",
    "bev": 112635,
    "total": 884506
  },
  {
    "x": "2029-11-01T00:00:00.000Z",
    "bev": 114512,
    "total": 884518
  },
  {
    "x": "2029-12-01T00:00:00.000Z",
    "bev": 116405,
    "total": 884529
  },
  {
    "x": "2030-01-01T00:00:00.000Z",
    "bev": 118313,
    "total": 884541
  },
  {
    "x": "2030-02-01T00:00:00.000Z",
    "bev": 120235,
    "total": 884552
  },
  {
    "x": "2030-03-01T00:00:00.000Z",
    "bev": 122172,
    "total": 884563
  },
  {
    "x": "2030-04-01T00:00:00.000Z",
    "bev": 124123,
    "total": 884574
  },
  {
    "x": "2030-05-01T00:00:00.000Z",
    "bev": 126089,
    "total": 884585
  },
  {
    "x": "2030-06-01T00:00:00.000Z",
    "bev": 128069,
    "total": 884596
  },
  {
    "x": "2030-07-01T00:00:00.000Z",
    "bev": 130063,
    "total": 884606
  },
  {
    "x": "2030-08-01T00:00:00.000Z",
    "bev": 132072,
    "total": 884616
  },
  {
    "x": "2030-09-01T00:00:00.000Z",
    "bev": 134095,
    "total": 884626
  },
  {
    "x": "2030-10-01T00:00:00.000Z",
    "bev": 136132,
    "total": 884636
  },
  {
    "x": "2030-11-01T00:00:00.000Z",
    "bev": 138183,
    "total": 884645
  },
  {
    "x": "2030-12-01T00:00:00.000Z",
    "bev": 140249,
    "total": 884655
  },
  {
    "x": "2031-01-01T00:00:00.000Z",
    "bev": 142328,
    "total": 884664
  },
  {
    "x": "2031-02-01T00:00:00.000Z",
    "bev": 144421,
    "total": 884673
  },
  {
    "x": "2031-03-01T00:00:00.000Z",
    "bev": 146527,
    "total": 884682
  },
  {
    "x": "2031-04-01T00:00:00.000Z",
    "bev": 148648,
    "total": 884691
  },
  {
    "x": "2031-05-01T00:00:00.000Z",
    "bev": 150781,
    "total": 884700
  },
  {
    "x": "2031-06-01T00:00:00.000Z",
    "bev": 152929,
    "total": 884708
  },
  {
    "x": "2031-07-01T00:00:00.000Z",
    "bev": 155089,
    "total": 884717
  },
  {
    "x": "2031-08-01T00:00:00.000Z",
    "bev": 157263,
    "total": 884725
  },
  {
    "x": "2031-09-01T00:00:00.000Z",
    "bev": 159450,
    "total": 884733
  },
  {
    "x": "2031-10-01T00:00:00.000Z",
    "bev": 161650,
    "total": 884741
  },
  {
    "x": "2031-11-01T00:00:00.000Z",
    "bev": 163863,
    "total": 884749
  },
  {
    "x": "2031-12-01T00:00:00.000Z",
    "bev": 166089,
    "total": 884757
  },
  {
    "x": "2032-01-01T00:00:00.000Z",
    "bev": 168328,
    "total": 884764
  },
  {
    "x": "2032-02-01T00:00:00.000Z",
    "bev": 170579,
    "total": 884772
  },
  {
    "x": "2032-03-01T00:00:00.000Z",
    "bev": 172842,
    "total": 884779
  },
  {
    "x": "2032-04-01T00:00:00.000Z",
    "bev": 175118,
    "total": 884787
  },
  {
    "x": "2032-05-01T00:00:00.000Z",
    "bev": 177407,
    "total": 884794
  },
  {
    "x": "2032-06-01T00:00:00.000Z",
    "bev": 179707,
    "total": 884801
  },
  {
    "x": "2032-07-01T00:00:00.000Z",
    "bev": 182019,
    "total": 884808
  },
  {
    "x": "2032-08-01T00:00:00.000Z",
    "bev": 184344,
    "total": 884815
  },
  {
    "x": "2032-09-01T00:00:00.000Z",
    "bev": 186680,
    "total": 884821
  },
  {
    "x": "2032-10-01T00:00:00.000Z",
    "bev": 189027,
    "total": 884828
  },
  {
    "x": "2032-11-01T00:00:00.000Z",
    "bev": 191386,
    "total": 884835
  },
  {
    "x": "2032-12-01T00:00:00.000Z",
    "bev": 193757,
    "total": 884841
  },
  {
    "x": "2033-01-01T00:00:00.000Z",
    "bev": 196139,
    "total": 884847
  },
  {
    "x": "2033-02-01T00:00:00.000Z",
    "bev": 198531,
    "total": 884854
  },
  {
    "x": "2033-03-01T00:00:00.000Z",
    "bev": 200935,
    "total": 884860
  },
  {
    "x": "2033-04-01T00:00:00.000Z",
    "bev": 203350,
    "total": 884866
  },
  {
    "x": "2033-05-01T00:00:00.000Z",
    "bev": 205775,
    "total": 884872
  },
  {
    "x": "2033-06-01T00:00:00.000Z",
    "bev": 208211,
    "total": 884878
  },
  {
    "x": "2033-07-01T00:00:00.000Z",
    "bev": 210657,
    "total": 884884
  },
  {
    "x": "2033-08-01T00:00:00.000Z",
    "bev": 213113,
    "total": 884890
  },
  {
    "x": "2033-09-01T00:00:00.000Z",
    "bev": 215580,
    "total": 884896
  },
  {
    "x": "2033-10-01T00:00:00.000Z",
    "bev": 218056,
    "total": 884901
  },
  {
    "x": "2033-11-01T00:00:00.000Z",
    "bev": 220542,
    "total": 884907
  },
  {
    "x": "2033-12-01T00:00:00.000Z",
    "bev": 223038,
    "total": 884912
  },
  {
    "x": "2034-01-01T00:00:00.000Z",
    "bev": 225543,
    "total": 884918
  },
  {
    "x": "2034-02-01T00:00:00.000Z",
    "bev": 228058,
    "total": 884923
  },
  {
    "x": "2034-03-01T00:00:00.000Z",
    "bev": 230582,
    "total": 884929
  },
  {
    "x": "2034-04-01T00:00:00.000Z",
    "bev": 233114,
    "total": 884934
  },
  {
    "x": "2034-05-01T00:00:00.000Z",
    "bev": 235656,
    "total": 884939
  },
  {
    "x": "2034-06-01T00:00:00.000Z",
    "bev": 238206,
    "total": 884945
  },
  {
    "x": "2034-07-01T00:00:00.000Z",
    "bev": 240765,
    "total": 884950
  },
  {
    "x": "2034-08-01T00:00:00.000Z",
    "bev": 243333,
    "total": 884955
  },
  {
    "x": "2034-09-01T00:00:00.000Z",
    "bev": 245908,
    "total": 884960
  },
  {
    "x": "2034-10-01T00:00:00.000Z",
    "bev": 248492,
    "total": 884965
  },
  {
    "x": "2034-11-01T00:00:00.000Z",
    "bev": 251083,
    "total": 884970
  },
  {
    "x": "2034-12-01T00:00:00.000Z",
    "bev": 253682,
    "total": 884975
  },
  {
    "x": "2035-01-01T00:00:00.000Z",
    "bev": 256289,
    "total": 884980
  },
  {
    "x": "2035-02-01T00:00:00.000Z",
    "bev": 258903,
    "total": 884985
  },
  {
    "x": "2035-03-01T00:00:00.000Z",
    "bev": 261524,
    "total": 884990
  },
  {
    "x": "2035-04-01T00:00:00.000Z",
    "bev": 264152,
    "total": 884995
  },
  {
    "x": "2035-05-01T00:00:00.000Z",
    "bev": 266788,
    "total": 885000
  },
  {
    "x": "2035-06-01T00:00:00.000Z",
    "bev": 269430,
    "total": 885004
  },
  {
    "x": "2035-07-01T00:00:00.000Z",
    "bev": 272078,
    "total": 885009
  },
  {
    "x": "2035-08-01T00:00:00.000Z",
    "bev": 274733,
    "total": 885014
  },
  {
    "x": "2035-09-01T00:00:00.000Z",
    "bev": 277394,
    "total": 885019
  },
  {
    "x": "2035-10-01T00:00:00.000Z",
    "bev": 280061,
    "total": 885023
  },
  {
    "x": "2035-11-01T00:00:00.000Z",
    "bev": 282734,
    "total": 885028
  },
  {
    "x": "2035-12-01T00:00:00.000Z",
    "bev": 285413,
    "total": 885033
  },
  {
    "x": "2036-01-01T00:00:00.000Z",
    "bev": 288097,
    "total": 885037
  },
  {
    "x": "2036-02-01T00:00:00.000Z",
    "bev": 290786,
    "total": 885042
  },
  {
    "x": "2036-03-01T00:00:00.000Z",
    "bev": 293481,
    "total": 885046
  },
  {
    "x": "2036-04-01T00:00:00.000Z",
    "bev": 296180,
    "total": 885051
  },
  {
    "x": "2036-05-01T00:00:00.000Z",
    "bev": 298884,
    "total": 885056
  },
  {
    "x": "2036-06-01T00:00:00.000Z",
    "bev": 301593,
    "total": 885060
  },
  {
    "x": "2036-07-01T00:00:00.000Z",
    "bev": 304307,
    "total": 885065
  },
  {
    "x": "2036-08-01T00:00:00.000Z",
    "bev": 307024,
    "total": 885069
  },
  {
    "x": "2036-09-01T00:00:00.000Z",
    "bev": 309746,
    "total": 885074
  },
  {
    "x": "2036-10-01T00:00:00.000Z",
    "bev": 312471,
    "total": 885078
  },
  {
    "x": "2036-11-01T00:00:00.000Z",
    "bev": 315201,
    "total": 885083
  },
  {
    "x": "2036-12-01T00:00:00.000Z",
    "bev": 317934,
    "total": 885087
  },
  {
    "x": "2037-01-01T00:00:00.000Z",
    "bev": 320670,
    "total": 885092
  },
  {
    "x": "2037-02-01T00:00:00.000Z",
    "bev": 323409,
    "total": 885096
  },
  {
    "x": "2037-03-01T00:00:00.000Z",
    "bev": 326151,
    "total": 885101
  },
  {
    "x": "2037-04-01T00:00:00.000Z",
    "bev": 328897,
    "total": 885105
  },
  {
    "x": "2037-05-01T00:00:00.000Z",
    "bev": 331644,
    "total": 885110
  },
  {
    "x": "2037-06-01T00:00:00.000Z",
    "bev": 334394,
    "total": 885114
  },
  {
    "x": "2037-07-01T00:00:00.000Z",
    "bev": 337147,
    "total": 885119
  },
  {
    "x": "2037-08-01T00:00:00.000Z",
    "bev": 339901,
    "total": 885123
  },
  {
    "x": "2037-09-01T00:00:00.000Z",
    "bev": 342658,
    "total": 885127
  },
  {
    "x": "2037-10-01T00:00:00.000Z",
    "bev": 345416,
    "total": 885132
  },
  {
    "x": "2037-11-01T00:00:00.000Z",
    "bev": 348175,
    "total": 885136
  },
  {
    "x": "2037-12-01T00:00:00.000Z",
    "bev": 350936,
    "total": 885141
  },
  {
    "x": "2038-01-01T00:00:00.000Z",
    "bev": 353698,
    "total": 885145
  },
  {
    "x": "2038-02-01T00:00:00.000Z",
    "bev": 356461,
    "total": 885150
  },
  {
    "x": "2038-03-01T00:00:00.000Z",
    "bev": 359225,
    "total": 885154
  },
  {
    "x": "2038-04-01T00:00:00.000Z",
    "bev": 361989,
    "total": 885159
  },
  {
    "x": "2038-05-01T00:00:00.000Z",
    "bev": 364754,
    "total": 885163
  },
  {
    "x": "2038-06-01T00:00:00.000Z",
    "bev": 367519,
    "total": 885168
  },
  {
    "x": "2038-07-01T00:00:00.000Z",
    "bev": 370284,
    "total": 885172
  },
  {
    "x": "2038-08-01T00:00:00.000Z",
    "bev": 373049,
    "total": 885177
  },
  {
    "x": "2038-09-01T00:00:00.000Z",
    "bev": 375813,
    "total": 885181
  },
  {
    "x": "2038-10-01T00:00:00.000Z",
    "bev": 378577,
    "total": 885186
  },
  {
    "x": "2038-11-01T00:00:00.000Z",
    "bev": 381340,
    "total": 885190
  },
  {
    "x": "2038-12-01T00:00:00.000Z",
    "bev": 384103,
    "total": 885195
  },
  {
    "x": "2039-01-01T00:00:00.000Z",
    "bev": 386864,
    "total": 885199
  },
  {
    "x": "2039-02-01T00:00:00.000Z",
    "bev": 389624,
    "total": 885204
  },
  {
    "x": "2039-03-01T00:00:00.000Z",
    "bev": 392382,
    "total": 885209
  },
  {
    "x": "2039-04-01T00:00:00.000Z",
    "bev": 395139,
    "total": 885213
  },
  {
    "x": "2039-05-01T00:00:00.000Z",
    "bev": 397894,
    "total": 885218
  },
  {
    "x": "2039-06-01T00:00:00.000Z",
    "bev": 400646,
    "total": 885222
  },
  {
    "x": "2039-07-01T00:00:00.000Z",
    "bev": 403397,
    "total": 885227
  },
  {
    "x": "2039-08-01T00:00:00.000Z",
    "bev": 406145,
    "total": 885231
  },
  {
    "x": "2039-09-01T00:00:00.000Z",
    "bev": 408890,
    "total": 885236
  },
  {
    "x": "2039-10-01T00:00:00.000Z",
    "bev": 411633,
    "total": 885240
  },
  {
    "x": "2039-11-01T00:00:00.000Z",
    "bev": 414373,
    "total": 885245
  },
  {
    "x": "2039-12-01T00:00:00.000Z",
    "bev": 417109,
    "total": 885249
  }
]