[
  {
    "x": "2022-01-01T00:00:00.000+01:00",
    "bev": 1,
    "phev": 0,
    "hybrid": null,
    "other": 6,
    "petrol": 0,
    "disel": 957,
    "total": 964
  },
  {
    "x": "2022-04-01T00:00:00.000+02:00",
    "bev": 0,
    "phev": 0,
    "hybrid": 0,
    "other": 18,
    "petrol": 0,
    "disel": 773,
    "total": 791
  },
  {
    "x": "2022-07-01T00:00:00.000+02:00",
    "bev": 0,
    "phev": 0,
    "hybrid": 0,
    "other": 1,
    "petrol": 0,
    "disel": 900,
    "total": 901
  },
  {
    "x": "2022-10-01T00:00:00.000+02:00",
    "bev": 0,
    "phev": 0,
    "hybrid": 0,
    "other": 8,
    "petrol": 0,
    "disel": 1423,
    "total": 1431
  },
  {
    "x": "2023-01-01T00:00:00.000+01:00",
    "bev": 0,
    "phev": 0,
    "hybrid": null,
    "other": 13,
    "petrol": 0,
    "disel": 1372,
    "total": 1385
  },
  {
    "x": "2023-04-01T00:00:00.000+02:00",
    "bev": 0,
    "phev": 0,
    "hybrid": 0,
    "other": 2,
    "petrol": 0,
    "disel": 1276,
    "total": 1278
  },
  {
    "x": "2023-07-01T00:00:00.000+02:00",
    "bev": 0,
    "phev": 0,
    "hybrid": 0,
    "other": 2,
    "petrol": 0,
    "disel": 1473,
    "total": 1475
  },
  {
    "x": "2023-10-01T00:00:00.000+02:00",
    "bev": 1,
    "phev": 0,
    "hybrid": 0,
    "other": 7,
    "petrol": 0,
    "disel": 2021,
    "total": 2029
  },
  {
    "x": "2024-01-01T00:00:00.000+01:00",
    "bev": 0,
    "phev": 0,
    "hybrid": null,
    "other": 0,
    "petrol": 0,
    "disel": 1424,
    "total": 1424
  },
  {
    "x": "2024-04-01T00:00:00.000+02:00",
    "bev": 0,
    "phev": 0,
    "hybrid": 0,
    "other": 1,
    "petrol": 0,
    "disel": 1536,
    "total": 1537
  },
  {
    "x": "2024-07-01T00:00:00.000+02:00",
    "bev": 0,
    "phev": 0,
    "hybrid": 0,
    "other": 8,
    "petrol": 0,
    "disel": 1152,
    "total": 1160
  }
]