[
  {
    "x": "2022-01-01T00:00:00.000Z",
    "bev": 0,
    "total": 22976
  },
  {
    "x": "2022-04-01T00:00:00.000Z",
    "bev": 7,
    "total": 22939
  },
  {
    "x": "2022-07-01T00:00:00.000Z",
    "bev": 7,
    "total": 22881
  },
  {
    "x": "2022-10-01T00:00:00.000Z",
    "bev": 18,
    "total": 22826
  },
  {
    "x": "2023-01-01T00:00:00.000Z",
    "bev": 25,
    "total": 22863
  },
  {
    "x": "2023-04-01T00:00:00.000Z",
    "bev": 35,
    "total": 22849
  },
  {
    "x": "2023-07-01T00:00:00.000Z",
    "bev": 40,
    "total": 22827
  },
  {
    "x": "2023-10-01T00:00:00.000Z",
    "bev": 69,
    "total": 22770
  },
  {
    "x": "2024-01-01T00:00:00.000Z",
    "bev": 130,
    "total": 22893
  },
  {
    "x": "2024-04-01T00:00:00.000Z",
    "bev": 286,
    "total": 23051
  },
  {
    "x": "2024-07-01T00:00:00.000Z",
    "bev": 290,
    "total": 23024
  },
  {
    "x": "2024-10-01T00:00:00.000Z",
    "bev": 296,
    "total": 22949
  },
  {
    "x": "2025-01-01T00:00:00.000Z",
    "bev": 305,
    "total": 22994
  },
  {
    "x": "2025-04-01T00:00:00.000Z",
    "bev": 313,
    "total": 23027
  },
  {
    "x": "2025-07-01T00:00:00.000Z",
    "bev": 313,
    "total": 23010
  },
  {
    "x": "2025-10-01T00:00:00.000Z",
    "bev": 322,
    "total": 22962
  },
  {
    "x": "2026-01-01T00:00:00.000Z",
    "bev": 347,
    "total": 22963
  },
  {
    "x": "2026-04-01T00:00:00.000Z",
    "bev": 373,
    "total": 22965
  },
  {
    "x": "2026-07-01T00:00:00.000Z",
    "bev": 399,
    "total": 22966
  },
  {
    "x": "2026-10-01T00:00:00.000Z",
    "bev": 426,
    "total": 22968
  },
  {
    "x": "2027-01-01T00:00:00.000Z",
    "bev": 454,
    "total": 22969
  },
  {
    "x": "2027-04-01T00:00:00.000Z",
    "bev": 483,
    "total": 22970
  },
  {
    "x": "2027-07-01T00:00:00.000Z",
    "bev": 512,
    "total": 22972
  },
  {
    "x": "2027-10-01T00:00:00.000Z",
    "bev": 542,
    "total": 22973
  },
  {
    "x": "2028-01-01T00:00:00.000Z",
    "bev": 572,
    "total": 22974
  },
  {
    "x": "2028-04-01T00:00:00.000Z",
    "bev": 604,
    "total": 22975
  },
  {
    "x": "2028-07-01T00:00:00.000Z",
    "bev": 636,
    "total": 22976
  },
  {
    "x": "2028-10-01T00:00:00.000Z",
    "bev": 668,
    "total": 22978
  },
  {
    "x": "2029-01-01T00:00:00.000Z",
    "bev": 702,
    "total": 22979
  },
  {
    "x": "2029-04-01T00:00:00.000Z",
    "bev": 736,
    "total": 22980
  },
  {
    "x": "2029-07-01T00:00:00.000Z",
    "bev": 771,
    "total": 22981
  },
  {
    "x": "2029-10-01T00:00:00.000Z",
    "bev": 807,
    "total": 22982
  },
  {
    "x": "2030-01-01T00:00:00.000Z",
    "bev": 844,
    "total": 22983
  },
  {
    "x": "2030-04-01T00:00:00.000Z",
    "bev": 881,
    "total": 22984
  },
  {
    "x": "2030-07-01T00:00:00.000Z",
    "bev": 919,
    "total": 22985
  },
  {
    "x": "2030-10-01T00:00:00.000Z",
    "bev": 958,
    "total": 22986
  },
  {
    "x": "2031-01-01T00:00:00.000Z",
    "bev": 997,
    "total": 22987
  },
  {
    "x": "2031-04-01T00:00:00.000Z",
    "bev": 1038,
    "total": 22988
  },
  {
    "x": "2031-07-01T00:00:00.000Z",
    "bev": 1079,
    "total": 22989
  },
  {
    "x": "2031-10-01T00:00:00.000Z",
    "bev": 1121,
    "total": 22990
  },
  {
    "x": "2032-01-01T00:00:00.000Z",
    "bev": 1164,
    "total": 22991
  },
  {
    "x": "2032-04-01T00:00:00.000Z",
    "bev": 1207,
    "total": 22992
  },
  {
    "x": "2032-07-01T00:00:00.000Z",
    "bev": 1252,
    "total": 22992
  },
  {
    "x": "2032-10-01T00:00:00.000Z",
    "bev": 1297,
    "total": 22993
  },
  {
    "x": "2033-01-01T00:00:00.000Z",
    "bev": 1343,
    "total": 22994
  },
  {
    "x": "2033-04-01T00:00:00.000Z",
    "bev": 1389,
    "total": 22995
  },
  {
    "x": "2033-07-01T00:00:00.000Z",
    "bev": 1437,
    "total": 22996
  },
  {
    "x": "2033-10-01T00:00:00.000Z",
    "bev": 1485,
    "total": 22996
  },
  {
    "x": "2034-01-01T00:00:00.000Z",
    "bev": 1534,
    "total": 22997
  },
  {
    "x": "2034-04-01T00:00:00.000Z",
    "bev": 1584,
    "total": 22998
  },
  {
    "x": "2034-07-01T00:00:00.000Z",
    "bev": 1635,
    "total": 22999
  },
  {
    "x": "2034-10-01T00:00:00.000Z",
    "bev": 1686,
    "total": 22999
  },
  {
    "x": "2035-01-01T00:00:00.000Z",
    "bev": 1738,
    "total": 23000
  },
  {
    "x": "2035-04-01T00:00:00.000Z",
    "bev": 1791,
    "total": 23001
  },
  {
    "x": "2035-07-01T00:00:00.000Z",
    "bev": 1845,
    "total": 23001
  },
  {
    "x": "2035-10-01T00:00:00.000Z",
    "bev": 1899,
    "total": 23002
  },
  {
    "x": "2036-01-01T00:00:00.000Z",
    "bev": 1955,
    "total": 23003
  },
  {
    "x": "2036-04-01T00:00:00.000Z",
    "bev": 2011,
    "total": 23003
  },
  {
    "x": "2036-07-01T00:00:00.000Z",
    "bev": 2067,
    "total": 23004
  },
  {
    "x": "2036-10-01T00:00:00.000Z",
    "bev": 2125,
    "total": 23005
  },
  {
    "x": "2037-01-01T00:00:00.000Z",
    "bev": 2183,
    "total": 23005
  },
  {
    "x": "2037-04-01T00:00:00.000Z",
    "bev": 2242,
    "total": 23006
  },
  {
    "x": "2037-07-01T00:00:00.000Z",
    "bev": 2301,
    "total": 23006
  },
  {
    "x": "2037-10-01T00:00:00.000Z",
    "bev": 2362,
    "total": 23007
  },
  {
    "x": "2038-01-01T00:00:00.000Z",
    "bev": 2423,
    "total": 23007
  },
  {
    "x": "2038-04-01T00:00:00.000Z",
    "bev": 2484,
    "total": 23008
  },
  {
    "x": "2038-07-01T00:00:00.000Z",
    "bev": 2547,
    "total": 23009
  },
  {
    "x": "2038-10-01T00:00:00.000Z",
    "bev": 2610,
    "total": 23009
  },
  {
    "x": "2039-01-01T00:00:00.000Z",
    "bev": 2673,
    "total": 23010
  },
  {
    "x": "2039-04-01T00:00:00.000Z",
    "bev": 2737,
    "total": 23010
  },
  {
    "x": "2039-07-01T00:00:00.000Z",
    "bev": 2802,
    "total": 23011
  },
  {
    "x": "2039-10-01T00:00:00.000Z",
    "bev": 2868,
    "total": 23011
  },
  {
    "x": "2040-01-01T00:00:00.000Z",
    "bev": 2934,
    "total": 23012
  }
]